env_config.py
py_env_config-0.1.2.dist-info/DESCRIPTION.rst
py_env_config-0.1.2.dist-info/METADATA
py_env_config-0.1.2.dist-info/RECORD
py_env_config-0.1.2.dist-info/WHEEL
py_env_config-0.1.2.dist-info/metadata.json
py_env_config-0.1.2.dist-info/top_level.txt
