Metadata-Version: 2.0
Name: py-env-config
Version: 0.1.2
Summary: A tool for configuring your application via environment variables
Home-page: https://github.com/timmartin19/env_config
Author: Tim Martin
Author-email: tim@timmartin.me
License: MIT license
Keywords: env_config environment variable configuration json config env envvar python
Platform: UNKNOWN
Classifier: Development Status :: 2 - Pre-Alpha
Classifier: Intended Audience :: Developers
Classifier: License :: OSI Approved :: MIT License
Classifier: Natural Language :: English
Classifier: Programming Language :: Python :: 2
Classifier: Programming Language :: Python :: 2.6
Classifier: Programming Language :: Python :: 2.7
Classifier: Programming Language :: Python :: 3
Classifier: Programming Language :: Python :: 3.3
Classifier: Programming Language :: Python :: 3.4
Classifier: Programming Language :: Python :: 3.5
